lazyopencode/__init__.py
lazyopencode/__main__.py
lazyopencode/_version.py
lazyopencode/app.py
lazyopencode/bindings.py
lazyopencode/themes.py
lazyopencode/mixins/filtering.py
lazyopencode/mixins/help.py
lazyopencode/mixins/navigation.py
lazyopencode/models/__init__.py
lazyopencode/models/customization.py
lazyopencode/services/__init__.py
lazyopencode/services/discovery.py
lazyopencode/services/gitignore_filter.py
lazyopencode/services/writer.py
lazyopencode/services/claude_code/__init__.py
lazyopencode/services/claude_code/discovery.py
lazyopencode/services/claude_code/plugin_loader.py
lazyopencode/services/claude_code/parsers/__init__.py
lazyopencode/services/claude_code/parsers/agent.py
lazyopencode/services/claude_code/parsers/command.py
lazyopencode/services/claude_code/parsers/skill.py
lazyopencode/services/parsers/__init__.py
lazyopencode/services/parsers/agent.py
lazyopencode/services/parsers/command.py
lazyopencode/services/parsers/mcp.py
lazyopencode/services/parsers/plugin.py
lazyopencode/services/parsers/rules.py
lazyopencode/services/parsers/skill.py
lazyopencode/services/parsers/tool.py
lazyopencode/styles/app.tcss
lazyopencode/widgets/__init__.py
lazyopencode/widgets/app_footer.py
lazyopencode/widgets/combined_panel.py
lazyopencode/widgets/delete_confirm.py
lazyopencode/widgets/detail_pane.py
lazyopencode/widgets/filter_input.py
lazyopencode/widgets/level_selector.py
lazyopencode/widgets/status_panel.py
lazyopencode/widgets/type_panel.py
lazyopencode/widgets/helpers/__init__.py
lazyopencode/widgets/helpers/rendering.py
lazyopencode-0.2.1.dist-info/METADATA
lazyopencode-0.2.1.dist-info/WHEEL
lazyopencode-0.2.1.dist-info/entry_points.txt
lazyopencode-0.2.1.dist-info/licenses/LICENSE
lazyopencode-0.2.1.dist-info/RECORD
