Metadata-Version: 2.4
Name: lazyopencode
Version: 0.2.1
Summary: A lazygit-style TUI for visualizing OpenCode customizations
Project-URL: Homepage, https://github.com/nikiforovall/lazyopencode
Project-URL: Repository, https://github.com/nikiforovall/lazyopencode
Author: nikiforovall
License-Expression: MIT
License-File: LICENSE
Keywords: cli,opencode,textual,tui
Classifier: Development Status :: 3 - Alpha
Classifier: Environment :: Console
Classifier: Intended Audience :: Developers
Classifier: License :: OSI Approved :: MIT License
Classifier: Operating System :: OS Independent
Classifier: Programming Language :: Python :: 3
Classifier: Programming Language :: Python :: 3.11
Classifier: Programming Language :: Python :: 3.12
Classifier: Topic :: Software Development :: User Interfaces
Requires-Python: >=3.11
Requires-Dist: pathspec>=0.12.0
Requires-Dist: pyperclip>=1.9.0
Requires-Dist: pyyaml>=6.0
Requires-Dist: rich>=13.0.0
Requires-Dist: textual>=0.89.0
Provides-Extra: dev
Requires-Dist: mypy>=1.13.0; extra == 'dev'
Requires-Dist: pytest-asyncio>=0.24.0; extra == 'dev'
Requires-Dist: pytest-textual-snapshot>=1.0.0; extra == 'dev'
Requires-Dist: pytest>=8.0.0; extra == 'dev'
Requires-Dist: ruff>=0.8.0; extra == 'dev'
